flyteidl/__init__.py
flyteidl/py.typed
flyteidl/admin/__init__.py
flyteidl/admin/common_pb2.py
flyteidl/admin/common_pb2.pyi
flyteidl/admin/common_pb2_grpc.py
flyteidl/admin/event_pb2.py
flyteidl/admin/event_pb2.pyi
flyteidl/admin/event_pb2_grpc.py
flyteidl/admin/execution_pb2.py
flyteidl/admin/execution_pb2.pyi
flyteidl/admin/execution_pb2_grpc.py
flyteidl/admin/launch_plan_pb2.py
flyteidl/admin/launch_plan_pb2.pyi
flyteidl/admin/launch_plan_pb2_grpc.py
flyteidl/admin/matchable_resource_pb2.py
flyteidl/admin/matchable_resource_pb2.pyi
flyteidl/admin/matchable_resource_pb2_grpc.py
flyteidl/admin/node_execution_pb2.py
flyteidl/admin/node_execution_pb2.pyi
flyteidl/admin/node_execution_pb2_grpc.py
flyteidl/admin/notification_pb2.py
flyteidl/admin/notification_pb2.pyi
flyteidl/admin/notification_pb2_grpc.py
flyteidl/admin/project_domain_attributes_pb2.py
flyteidl/admin/project_domain_attributes_pb2.pyi
flyteidl/admin/project_domain_attributes_pb2_grpc.py
flyteidl/admin/project_pb2.py
flyteidl/admin/project_pb2.pyi
flyteidl/admin/project_pb2_grpc.py
flyteidl/admin/schedule_pb2.py
flyteidl/admin/schedule_pb2.pyi
flyteidl/admin/schedule_pb2_grpc.py
flyteidl/admin/task_execution_pb2.py
flyteidl/admin/task_execution_pb2.pyi
flyteidl/admin/task_execution_pb2_grpc.py
flyteidl/admin/task_pb2.py
flyteidl/admin/task_pb2.pyi
flyteidl/admin/task_pb2_grpc.py
flyteidl/admin/version_pb2.py
flyteidl/admin/version_pb2.pyi
flyteidl/admin/version_pb2_grpc.py
flyteidl/admin/workflow_attributes_pb2.py
flyteidl/admin/workflow_attributes_pb2.pyi
flyteidl/admin/workflow_attributes_pb2_grpc.py
flyteidl/admin/workflow_pb2.py
flyteidl/admin/workflow_pb2.pyi
flyteidl/admin/workflow_pb2_grpc.py
flyteidl/core/__init__.py
flyteidl/core/catalog_pb2.py
flyteidl/core/catalog_pb2.pyi
flyteidl/core/catalog_pb2_grpc.py
flyteidl/core/compiler_pb2.py
flyteidl/core/compiler_pb2.pyi
flyteidl/core/compiler_pb2_grpc.py
flyteidl/core/condition_pb2.py
flyteidl/core/condition_pb2.pyi
flaightidl-0.1.1.dist-info/LICENSE
flaightidl-0.1.1.dist-info/METADATA
flaightidl-0.1.1.dist-info/NOTICE
flaightidl-0.1.1.dist-info/WHEEL
flaightidl-0.1.1.dist-info/top_level.txt
flaightidl-0.1.1.dist-info/RECORD
