Metadata-Version: 2.1
Name: flaightidl
Version: 0.1.1
Summary: IDL for Flyte Platform (Latch fork)
Home-page: UNKNOWN
Maintainer: maximsmol
Maintainer-email: max@latch.bio
License: UNKNOWN
Platform: UNKNOWN
License-File: LICENSE
License-File: NOTICE
